notebooks/__init__.py
notebooks/test_dataset.py
notebooks/test_planner.py
usa/__init__.py
usa/evaluation/__init__.py
usa/evaluation/path_length.py
usa/evaluation/semantics.py
usa/evaluation/trajectories.py
usa/evaluation/utils.py
usa/evaluation/visualize_semantics.py
usa/models/__init__.py
usa/models/clip.py
usa/models/point2emb.py
usa/models/sam.py
usa/planners/__init__.py
usa/planners/base.py
usa/planners/clip_sdf.py
usa/planners/common.py
usa/planners/occupancy_map.py
usa/scripts/__init__.py
usa/scripts/cli.py
usa/scripts/adhoc/__init__.py
usa/scripts/adhoc/distribution_estimates.py
usa/scripts/adhoc/get_pybullet_dataset.py
usa/scripts/adhoc/show_point_cloud.py
usa/tasks/__init__.py
usa/tasks/clip_sdf.py
usa/tasks/datasets/__init__.py
usa/tasks/datasets/home_robot.py
usa/tasks/datasets/posed_rgbd.py
usa/tasks/datasets/pybullet.py
usa/tasks/datasets/r3d.py
usa/tasks/datasets/replica_cad.py
usa/tasks/datasets/stretch.py
usa/tasks/datasets/types.py
usa/tasks/datasets/utils.py
usa_net-0.0.5.dist-info/METADATA
usa_net-0.0.5.dist-info/WHEEL
usa_net-0.0.5.dist-info/entry_points.txt
usa_net-0.0.5.dist-info/top_level.txt
usa_net-0.0.5.dist-info/RECORD
