Metadata-Version: 2.1
Name: usa-net
Version: 0.0.5
Summary: USA net project
Home-page: https://github.com/codekansas/usa-net
Author: Benjamin Bolte
Requires-Python: >=3.10
Requires-Dist: ffmpeg-python
Requires-Dist: ftfy
Requires-Dist: imageio
Requires-Dist: jupyter
Requires-Dist: matplotlib
Requires-Dist: ml-starter (==0.0.44)
Requires-Dist: more-itertools
Requires-Dist: numpy
Requires-Dist: numpy-quaternion
Requires-Dist: open3d
Requires-Dist: opencv-python
Requires-Dist: pandas
Requires-Dist: pyliblzfse
Requires-Dist: seaborn
Requires-Dist: torch (>=2.0.0)
Requires-Dist: torchvision (>=0.13.1)
Provides-Extra: dev
Requires-Dist: black ; extra == 'dev'
Requires-Dist: darglint ; extra == 'dev'
Requires-Dist: mypy ; extra == 'dev'
Requires-Dist: mypy-extensions ; extra == 'dev'
Requires-Dist: pytest ; extra == 'dev'
Requires-Dist: ruff ; extra == 'dev'
Requires-Dist: typing-extensions ; extra == 'dev'
Provides-Extra: ipynb
Requires-Dist: ipygany ; extra == 'ipynb'
Requires-Dist: ipywidgets ; extra == 'ipynb'
Requires-Dist: nbstripout ; extra == 'ipynb'
Requires-Dist: pre-commit ; extra == 'ipynb'
Requires-Dist: pybullet ; extra == 'ipynb'
Requires-Dist: pythreejs ; extra == 'ipynb'
Requires-Dist: pyvista ; extra == 'ipynb'
Requires-Dist: scikit-learn ; extra == 'ipynb'
Requires-Dist: scipy ; extra == 'ipynb'
Requires-Dist: trame ; extra == 'ipynb'
